rank_tracker/__init__.py
rank_tracker/tracker.py
tests/__init__.py
tests/test_tracker.py
gsc_rank_tracker-0.1.1.dist-info/METADATA
gsc_rank_tracker-0.1.1.dist-info/WHEEL
gsc_rank_tracker-0.1.1.dist-info/entry_points.txt
gsc_rank_tracker-0.1.1.dist-info/top_level.txt
gsc_rank_tracker-0.1.1.dist-info/RECORD
