Metadata-Version: 2.1
Name: gsc_rank_tracker
Version: 0.1.1
Summary: A basic rank tracker using Plotly and Google Search Console API.
Home-page: https://github.com/yourusername/rank_tracker
Author: Chris Lever SEO
Author-email: hello@chrisleverseo.com
Classifier: Programming Language :: Python :: 3
Classifier: License :: OSI Approved :: MIT License
Classifier: Operating System :: OS Independent
Requires-Python: >=3.6
Requires-Dist: pandas
Requires-Dist: plotly
Requires-Dist: google-auth-oauthlib
Requires-Dist: google-api-python-client
Requires-Dist: statsmodels
